mas/devops/__init__.py
mas/devops/aiservice.py
mas/devops/db2.py
mas/devops/ocp.py
mas/devops/olm.py
mas/devops/slack.py
mas/devops/sls.py
mas/devops/tekton.py
mas/devops/users.py
mas/devops/utils.py
mas/devops/data/__init__.py
mas/devops/data/ocp.yaml
mas/devops/data/catalogs/v8-230414-amd64.yaml
mas/devops/data/catalogs/v8-230518-amd64.yaml
mas/devops/data/catalogs/v8-230526-amd64.yaml
mas/devops/data/catalogs/v8-230616-amd64.yaml
mas/devops/data/catalogs/v8-230627-amd64.yaml
mas/devops/data/catalogs/v8-230721-amd64.yaml
mas/devops/data/catalogs/v8-230725-amd64.yaml
mas/devops/data/catalogs/v8-230829-amd64.yaml
mas/devops/data/catalogs/v8-230926-amd64.yaml
mas/devops/data/catalogs/v8-231004-amd64.yaml
mas/devops/data/catalogs/v8-231031-amd64.yaml
mas/devops/data/catalogs/v8-231128-amd64.yaml
mas/devops/data/catalogs/v8-231228-amd64.yaml
mas/devops/data/catalogs/v8-240130-amd64.yaml
mas/devops/data/catalogs/v8-240227-amd64.yaml
mas/devops/data/catalogs/v8-240326-amd64.yaml
mas/devops/data/catalogs/v8-240405-amd64.yaml
mas/devops/data/catalogs/v8-240430-amd64.yaml
mas/devops/data/catalogs/v8-240528-amd64.yaml
mas/devops/data/catalogs/v9-240625-amd64.yaml
mas/devops/data/catalogs/v9-240730-amd64.yaml
mas/devops/data/catalogs/v9-240827-amd64.yaml
mas/devops/data/catalogs/v9-241003-amd64.yaml
mas/devops/data/catalogs/v9-241107-amd64.yaml
mas/devops/data/catalogs/v9-241107-s390x.yaml
mas/devops/data/catalogs/v9-241205-amd64.yaml
mas/devops/data/catalogs/v9-241205-s390x.yaml
mas/devops/data/catalogs/v9-250109-amd64.yaml
mas/devops/data/catalogs/v9-250109-s390x.yaml
mas/devops/data/catalogs/v9-250206-amd64.yaml
mas/devops/data/catalogs/v9-250206-s390x.yaml
mas/devops/data/catalogs/v9-250306-amd64.yaml
mas/devops/data/catalogs/v9-250306-s390x.yaml
mas/devops/data/catalogs/v9-250403-amd64.yaml
mas/devops/data/catalogs/v9-250403-s390x.yaml
mas/devops/data/catalogs/v9-250501-amd64.yaml
mas/devops/data/catalogs/v9-250501-s390x.yaml
mas_devops-9.5.0.dist-info/licenses/LICENSE
mas_devops-9.5.0.dist-info/METADATA
mas_devops-9.5.0.dist-info/WHEEL
mas_devops-9.5.0.dist-info/top_level.txt
mas_devops-9.5.0.dist-info/RECORD
