Metadata-Version: 2.4
Name: mas-devops
Version: 9.5.0
Summary: Python for Maximo Application Suite Dev/Ops
Home-page: https://github.com/ibm-mas/python-devops
Author: David Parker
Author-email: parkerda@uk.ibm.com
License: Eclipse Public License - v1.0
Classifier: Development Status :: 4 - Beta
Classifier: Intended Audience :: Developers
Classifier: Operating System :: Microsoft :: Windows
Classifier: Operating System :: POSIX :: Linux
Classifier: Programming Language :: Python
Classifier: Programming Language :: Python :: 3.12
Classifier: Topic :: Communications
Classifier: Topic :: Internet
Classifier: Topic :: Software Development :: Libraries :: Python Modules
License-File: LICENSE
Requires-Dist: pyyaml
Requires-Dist: openshift
Requires-Dist: kubernetes
Requires-Dist: kubeconfig
Requires-Dist: jinja2
Requires-Dist: jinja2-base64-filters
Requires-Dist: semver
Requires-Dist: boto3
Requires-Dist: slack_sdk
Provides-Extra: dev
Requires-Dist: build; extra == "dev"
Requires-Dist: flake8; extra == "dev"
Requires-Dist: pytest; extra == "dev"
Requires-Dist: pytest-mock; extra == "dev"
Requires-Dist: requests-mock; extra == "dev"
Requires-Dist: setuptools; extra == "dev"
Provides-Extra: docs
Requires-Dist: mkdocs; extra == "docs"
Requires-Dist: mkdocs-material; extra == "docs"
Requires-Dist: mkdocstrings[python]; extra == "docs"
Requires-Dist: pymdown-extensions; extra == "docs"
Dynamic: author
Dynamic: author-email
Dynamic: classifier
Dynamic: description
Dynamic: home-page
Dynamic: license
Dynamic: license-file
Dynamic: provides-extra
Dynamic: requires-dist
Dynamic: summary
